setup.py
buckingham/__init__.py
buckingham.egg-info/PKG-INFO
buckingham.egg-info/SOURCES.txt
buckingham.egg-info/dependency_links.txt
buckingham.egg-info/not-zip-safe
buckingham.egg-info/top_level.txt